stubs/__init__.py
stubs/common.py
stubs/config.py
stubs/data_manipulation.py
stubs/mesh.py
stubs/model.py
stubs/model_assembly.py
stubs/model_building.py
stubs/solvers.py
fenics_stubs-0.1.10.dist-info/LICENSE
fenics_stubs-0.1.10.dist-info/METADATA
fenics_stubs-0.1.10.dist-info/WHEEL
fenics_stubs-0.1.10.dist-info/top_level.txt
fenics_stubs-0.1.10.dist-info/RECORD
