Metadata-Version: 2.1
Name: fenics-stubs
Version: 0.1.10
Summary: STUBS is a biophysical simulation library that provides a level of abstraction to models, making it easier for users to develop, share, and simulate their mathematical models.
Home-page: https://github.com/justinlaughlin/stubs
Author: Justin Laughlin
Author-email: justinglaughlin@gmail.com
License: LGPLv3
Platform: Linux
Platform: Mac OS-X
License-File: LICENSE
Requires-Dist: matplotlib
Requires-Dist: numpy (>=1.16.0)
Requires-Dist: pandas
Requires-Dist: Pint
Requires-Dist: scipy (>=1.1.0)
Requires-Dist: sympy
Requires-Dist: dataclasses
Requires-Dist: cached-property
Requires-Dist: pydantic
Requires-Dist: tabulate
Requires-Dist: termcolor
Requires-Dist: pytest
Requires-Dist: sphinx (==4.3.0)
